a_selenium_iframes_crawler/LICENSE
a_selenium_iframes_crawler/README.MD
a_selenium_iframes_crawler/__init__.py
a_selenium_iframes_crawler/requirements.txt
a_selenium_iframes_crawler/thirdparty.json
a_selenium_iframes_crawler-0.10.dist-info/LICENSE.rst
a_selenium_iframes_crawler-0.10.dist-info/METADATA
a_selenium_iframes_crawler-0.10.dist-info/WHEEL
a_selenium_iframes_crawler-0.10.dist-info/top_level.txt
a_selenium_iframes_crawler-0.10.dist-info/RECORD
